{
    "rmutp.ac.th.": {
        "queries": {
            "rmutp.ac.th./IN/A": {
                "answer": [
                    {
                        "id": "rmutp.ac.th./IN/A",
                        "warnings": [
                            {
                                "description": "No response was received until the UDP payload size was decreased, indicating that the server might be attempting to send a payload that exceeds the path maximum transmission unit (PMTU) size.  See RFC 6891, Sec. 6.2.6.",
                                "code": "PMTU_EXCEEDED",
                                "servers": [
                                    "203.158.144.1"
                                ],
                                "query_options": [
                                    "UDP_-_EDNS0_4096_D_NK"
                                ]
                            }
                        ]
                    }
                ]
            },
            "rmutp.ac.th./IN/NS": {
                "answer": [
                    {
                        "id": "rmutp.ac.th./IN/NS",
                        "warnings": [
                            {
                                "description": "No response was received until the UDP payload size was decreased, indicating that the server might be attempting to send a payload that exceeds the path maximum transmission unit (PMTU) size.  See RFC 6891, Sec. 6.2.6.",
                                "code": "PMTU_EXCEEDED",
                                "servers": [
                                    "203.158.144.1"
                                ],
                                "query_options": [
                                    "UDP_-_EDNS0_4096_D_NK"
                                ]
                            }
                        ]
                    }
                ]
            },
            "rmutp.ac.th./IN/SOA": {
                "answer": [
                    {
                        "id": "rmutp.ac.th./IN/SOA",
                        "warnings": [
                            {
                                "description": "No response was received until the UDP payload size was decreased, indicating that the server might be attempting to send a payload that exceeds the path maximum transmission unit (PMTU) size.  See RFC 6891, Sec. 6.2.6.",
                                "code": "PMTU_EXCEEDED",
                                "servers": [
                                    "203.158.144.1"
                                ],
                                "query_options": [
                                    "UDP_-_EDNS0_4096_D_NK",
                                    "UDP_-_EDNS0_4096_D_NK_0x20"
                                ]
                            }
                        ]
                    }
                ]
            },
            "rmutp.ac.th./IN/MX": {
                "answer": [
                    {
                        "id": "rmutp.ac.th./IN/MX",
                        "warnings": [
                            {
                                "description": "No response was received until the UDP payload size was decreased, indicating that the server might be attempting to send a payload that exceeds the path maximum transmission unit (PMTU) size.  See RFC 6891, Sec. 6.2.6.",
                                "code": "PMTU_EXCEEDED",
                                "servers": [
                                    "203.158.144.1"
                                ],
                                "query_options": [
                                    "UDP_-_EDNS0_4096_D_NK"
                                ]
                            }
                        ]
                    }
                ]
            },
            "rmutp.ac.th./IN/TXT": {
                "answer": [
                    {
                        "id": "rmutp.ac.th./IN/TXT",
                        "warnings": [
                            {
                                "description": "No response was received until the UDP payload size was decreased, indicating that the server might be attempting to send a payload that exceeds the path maximum transmission unit (PMTU) size.  See RFC 6891, Sec. 6.2.6.",
                                "code": "PMTU_EXCEEDED",
                                "servers": [
                                    "203.158.144.1"
                                ],
                                "query_options": [
                                    "UDP_-_EDNS0_4096_D_NK"
                                ]
                            }
                        ]
                    }
                ]
            },
            "rmutp.ac.th./IN/AAAA": {
                "answer": [
                    {
                        "id": "rmutp.ac.th./IN/AAAA",
                        "warnings": [
                            {
                                "description": "No response was received until the UDP payload size was decreased, indicating that the server might be attempting to send a payload that exceeds the path maximum transmission unit (PMTU) size.  See RFC 6891, Sec. 6.2.6.",
                                "code": "PMTU_EXCEEDED",
                                "servers": [
                                    "203.158.144.1"
                                ],
                                "query_options": [
                                    "UDP_-_EDNS0_4096_D_NK"
                                ]
                            }
                        ]
                    }
                ]
            },
            "rmutp.ac.th./IN/DNSKEY": {
                "answer": [
                    {
                        "id": "rmutp.ac.th./IN/DNSKEY",
                        "warnings": [
                            {
                                "description": "No response was received until the UDP payload size was decreased, indicating that the server might be attempting to send a payload that exceeds the path maximum transmission unit (PMTU) size.  See RFC 6891, Sec. 6.2.6.",
                                "code": "PMTU_EXCEEDED",
                                "servers": [
                                    "203.158.144.1"
                                ],
                                "query_options": [
                                    "UDP_-_EDNS0_4096_D_NK"
                                ]
                            }
                        ]
                    }
                ]
            },
            "r6eot.7meof.rmutp.ac.th./IN/A": {
                "nxdomain": [
                    {
                        "id": "r6eot.7meof.rmutp.ac.th./IN/A",
                        "warnings": [
                            {
                                "description": "No response was received until the UDP payload size was decreased, indicating that the server might be attempting to send a payload that exceeds the path maximum transmission unit (PMTU) size.  See RFC 6891, Sec. 6.2.6.",
                                "code": "PMTU_EXCEEDED",
                                "servers": [
                                    "203.158.144.1"
                                ],
                                "query_options": [
                                    "UDP_-_EDNS0_4096_D_NK"
                                ]
                            }
                        ]
                    }
                ]
            }
        }
    }
}